{
  "name": "auto_探索_异构模态一致性损失函数_构建包含_f1f70c",
  "file": "skills/auto_探索_异构模态一致性损失函数_构建包含_f1f70c.py",
  "description": "探索‘异构模态一致性损失函数’，构建包含物理定律约束的代码生成验证器。",
  "tags": [
    "auto_growth",
    "glm5_generated",
    "round_79",
    "general",
    "parallel"
  ],
  "created_at": "2026-03-25T18:14:51.541911",
  "forged_by": "growth_engine_v5_parallel",
  "source": "knowledge_gap",
  "source_node_id": "gap_79_G1_7937",
  "design_spec": {
    "name": "auto_探索_异构模态一致性损失函数_构建包含_f1f70c",
    "display_name": "探索‘异构模态一致性损失函数’，构建包含物理定律约束的代码生成验证器。",
    "functions": [
      {
        "name": "execute",
        "purpose": "探索‘异构模态一致性损失函数’，构建包含物理定律约束的代码生成验证器。",
        "params": [],
        "returns": "Dict"
      }
    ],
    "dependencies": [],
    "estimated_lines": 8
  }
}