{
  "name": "auto_在代码生成领域_验证_流畅性_与_可用性_378086",
  "file": "skills/auto_在代码生成领域_验证_流畅性_与_可用性_378086.py",
  "description": "在代码生成领域，验证'流畅性'与'可用性'的分离。AI能否在生成代码的同时，显式标注出代码中的'假设边界'（Assumption Boundaries），即明确指出哪部分代码是确定逻辑，哪部分是基于概率猜测？",
  "tags": [
    "auto_growth",
    "glm5_generated",
    "round_1",
    "software_engineering",
    "parallel"
  ],
  "created_at": "2026-03-24T07:26:29.549940",
  "forged_by": "growth_engine_v5_parallel",
  "source": "glm5_generated",
  "source_node_id": "td_1_Q6_2_5894",
  "design_spec": {
    "name": "auto_在代码生成领域_验证_流畅性_与_可用性_378086",
    "display_name": "在代码生成领域，验证'流畅性'与'可用性'的分离。AI能否在生成代码的同时，显式标注出代码中的'假设",
    "functions": [
      {
        "name": "execute",
        "purpose": "在代码生成领域，验证'流畅性'与'可用性'的分离。AI能否在生成代码的同时，显式标注出代码中的'假设边界'（Assumption Boundaries），即明确",
        "params": [],
        "returns": "Dict"
      }
    ],
    "dependencies": [],
    "estimated_lines": 251
  }
}