{
  "name": "auto_意图_结构双轨对齐生成器_融合能力_不_7d61ee",
  "file": "skills/auto_意图_结构双轨对齐生成器_融合能力_不_7d61ee.py",
  "description": "【意图-结构双轨对齐生成器】融合能力：不仅能生成代码，还能像解析隐喻一样，自动提取用户意图中的'结构骨架'（如'贪吃蛇'隐含的'边界碰撞'和'增长规则'），并将其转化为代码中的'显式约束对象'（Constraint Objects）。系统将不再仅仅生成代码行，而是生成'代码+结构化假定'的双层数据。例如，当用户说'像管理图书馆一样管理内存'，系统不仅写出代码，还生成一个结构化的JSON配置，明确锁定了'分类（内存池）、索引（指针映射）、借还（分配释放）'的逻辑映射，并标注出'逾期罚款（内存泄漏处理）'这一假设边界，供用户确认。这解决了代码'能用但逻辑偏差'的问题。",
  "tags": [
    "auto_growth",
    "glm5_generated",
    "round_78",
    "cross_domain",
    "parallel"
  ],
  "created_at": "2026-03-25T17:50:16.462339",
  "forged_by": "growth_engine_v5_parallel",
  "source": "collision",
  "source_node_id": "ho_78_O1_1115",
  "design_spec": {
    "name": "auto_意图_结构双轨对齐生成器_融合能力_不_7d61ee",
    "display_name": "【意图-结构双轨对齐生成器】融合能力：不仅能生成代码，还能像解析隐喻一样，自动提取用户意图中的'结构",
    "functions": [
      {
        "name": "execute",
        "purpose": "【意图-结构双轨对齐生成器】融合能力：不仅能生成代码，还能像解析隐喻一样，自动提取用户意图中的'结构骨架'（如'贪吃蛇'隐含的'边界碰撞'和'增长规则'），并将",
        "params": [],
        "returns": "Dict"
      }
    ],
    "dependencies": [],
    "estimated_lines": 8
  }
}