{
  "name": "auto_这是一种旨在发现_颠覆性创新_的推理引擎_ca559e",
  "file": "skills/auto_这是一种旨在发现_颠覆性创新_的推理引擎_ca559e.py",
  "description": "这是一种旨在发现‘颠覆性创新’的推理引擎。它不依赖传统的语义相似性，而是通过非欧几里得几何流形或拓扑学方法，寻找看似无关领域（如音乐赋格与商业谈判）之间的深层结构同构。该引擎不仅进行映射，还监测‘重叠固化’过程中的冲突率。当两个差异巨大的节点在强行融合时产生高冲突但逻辑自洽，系统即判定发现了新的‘知识临界点’（如临界阈值），从而自动生成新的真实节点，模拟人类跨学科创新的‘顿悟’时刻。",
  "tags": [
    "auto_growth",
    "glm5_generated",
    "round_27",
    "cross_domain",
    "parallel"
  ],
  "created_at": "2026-03-24T17:46:27.714384",
  "forged_by": "growth_engine_v5_parallel",
  "source": "glm5_generated",
  "source_node_id": "bu_27_P2_8447",
  "design_spec": {
    "name": "auto_这是一种旨在发现_颠覆性创新_的推理引擎_ca559e",
    "display_name": "这是一种旨在发现‘颠覆性创新’的推理引擎。它不依赖传统的语义相似性，而是通过非欧几里得几何流形或拓扑",
    "functions": [
      {
        "name": "execute",
        "purpose": "这是一种旨在发现‘颠覆性创新’的推理引擎。它不依赖传统的语义相似性，而是通过非欧几里得几何流形或拓扑学方法，寻找看似无关领域（如音乐赋格与商业谈判）之间的深层结",
        "params": [],
        "returns": "Dict"
      }
    ],
    "dependencies": [],
    "estimated_lines": 8
  }
}