{
  "name": "auto_基于认知负荷的动态信息架构系统_该系统不_b996c1",
  "file": "skills/auto_基于认知负荷的动态信息架构系统_该系统不_b996c1.py",
  "description": "基于认知负荷的动态信息架构系统。该系统不再仅仅依据数据本身的逻辑关系建模，而是实时监测用户的认知状态（如眼动追踪、交互延迟）。当检测到用户认知过载时，系统自动对信息进行'反范式化'处理，即主动引入数据冗余（如预计算结果、合并视图），牺牲存储空间以换取用户的'零延迟'理解。反之，在用户处于探索模式时，回归高范式模式以提供细节。这是将人脑的局限性强转为系统设计的核心参数。",
  "tags": [
    "auto_growth",
    "glm5_generated",
    "round_98",
    "cross_domain",
    "parallel"
  ],
  "created_at": "2026-03-26T01:07:18.794362",
  "forged_by": "growth_engine_v5_parallel",
  "source": "collision",
  "source_node_id": "ho_98_O1_8422",
  "design_spec": {
    "name": "auto_基于认知负荷的动态信息架构系统_该系统不_b996c1",
    "display_name": "基于认知负荷的动态信息架构系统。该系统不再仅仅依据数据本身的逻辑关系建模，而是实时监测用户的认知状态",
    "functions": [
      {
        "name": "execute",
        "purpose": "基于认知负荷的动态信息架构系统。该系统不再仅仅依据数据本身的逻辑关系建模，而是实时监测用户的认知状态（如眼动追踪、交互延迟）。当检测到用户认知过载时，系统自动对",
        "params": [],
        "returns": "Dict"
      }
    ],
    "dependencies": [],
    "estimated_lines": 239
  }
}