{
  "name": "auto_知识图谱中的_结构洞_挖掘与边缘压力测试_e4bc89",
  "file": "skills/auto_知识图谱中的_结构洞_挖掘与边缘压力测试_e4bc89.py",
  "description": "知识图谱中的'结构洞'挖掘与边缘压力测试：如何开发一个图遍历算法，主动寻找现有1595个技能节点之间的连接薄弱点（即结构洞），并针对这些空白区域自动生成'探索性假设'？这些假设是高风险高回报的证伪对象，用于验证现有知识网络的完备性。",
  "tags": [
    "auto_growth",
    "glm5_generated",
    "round_92",
    "graph_theory",
    "parallel"
  ],
  "created_at": "2026-03-25T23:09:38.938576",
  "forged_by": "growth_engine_v5_parallel",
  "source": "glm5_generated",
  "source_node_id": "td_92_Q3_1_9931",
  "design_spec": {
    "name": "auto_知识图谱中的_结构洞_挖掘与边缘压力测试_e4bc89",
    "display_name": "知识图谱中的'结构洞'挖掘与边缘压力测试：如何开发一个图遍历算法，主动寻找现有1595个技能节点之间",
    "functions": [
      {
        "name": "execute",
        "purpose": "知识图谱中的'结构洞'挖掘与边缘压力测试：如何开发一个图遍历算法，主动寻找现有1595个技能节点之间的连接薄弱点（即结构洞），并针对这些空白区域自动生成'探索性",
        "params": [],
        "returns": "Dict"
      }
    ],
    "dependencies": [],
    "estimated_lines": 387
  }
}